CHANGES.rst
CREDITS.rst
LICENSE.rst
MANIFEST.in
README.rst
setup.cfg
setup.py
nensbuild/__init__.py
nensbuild/build.py
nensbuild/tests.py
nensbuild.egg-info/PKG-INFO
nensbuild.egg-info/SOURCES.txt
nensbuild.egg-info/dependency_links.txt
nensbuild.egg-info/entry_points.txt
nensbuild.egg-info/not-zip-safe
nensbuild.egg-info/requires.txt
nensbuild.egg-info/top_level.txt