Metadata-Version: 1.1
Name: nensbuild
Version: 0.2
Summary: One step buildout build.
Home-page: http://github.com/nens/nensbuild
Author: Roland van Laar
Author-email: roland.vanlaar@nelen-schuurmans.nl
License: BSD
Platform: UNKNOWN
Classifier: Development Status :: 4 - Beta
Classifier: Environment :: Console
Classifier: Intended Audience :: Developers
Classifier: License :: OSI Approved :: BSD License
Classifier: Operating System :: Unix
Classifier: Programming Language :: Python :: 2.6
Classifier: Programming Language :: Python :: 2.7
Classifier: Topic :: Software Development :: Build Tools
